{
  "total_checks": 8435,
  "successful_checks": 8286,
  "failed_checks": 149,
  "success_rate": 98.2,
  "avg_response_time_ms": 4531.88,
  "median_response_time_ms": 3667.33,
  "min_response_time_ms": 31.11,
  "max_response_time_ms": 15097.51,
  "last_10_avg_response_time_ms": 5849.98,
  "last_10_successful": 10,
  "last_10_failed": 0,
  "last_10_success_rate": 100.0,
  "last_10_values": [
    {
      "measurement": 1,
      "timestamp": "2025-10-10T03:28:01",
      "response_time_ms": 42.75,
      "success": true
    },
    {
      "measurement": 2,
      "timestamp": "2025-10-10T03:29:03",
      "response_time_ms": 8479.92,
      "success": true
    },
    {
      "measurement": 3,
      "timestamp": "2025-10-10T03:30:13",
      "response_time_ms": 1390.38,
      "success": true
    },
    {
      "measurement": 4,
      "timestamp": "2025-10-10T03:31:16",
      "response_time_ms": 43.05,
      "success": true
    },
    {
      "measurement": 5,
      "timestamp": "2025-10-10T03:32:18",
      "response_time_ms": 9816.41,
      "success": true
    },
    {
      "measurement": 6,
      "timestamp": "2025-10-10T03:33:30",
      "response_time_ms": 42.49,
      "success": true
    },
    {
      "measurement": 7,
      "timestamp": "2025-10-10T03:34:32",
      "response_time_ms": 9527.3,
      "success": true
    },
    {
      "measurement": 8,
      "timestamp": "2025-10-10T03:35:43",
      "response_time_ms": 8782.76,
      "success": true
    },
    {
      "measurement": 9,
      "timestamp": "2025-10-10T03:36:54",
      "response_time_ms": 8604.88,
      "success": true
    },
    {
      "measurement": 10,
      "timestamp": "2025-10-10T03:38:04",
      "response_time_ms": 11769.84,
      "success": true
    }
  ],
  "last_updated": "2025-10-10T03:38:16.627344",
  "checker_version": "1.0"
}