{
  "total_checks": 42287,
  "successful_checks": 41889,
  "failed_checks": 398,
  "success_rate": 99.1,
  "avg_response_time_ms": 4383.8,
  "median_response_time_ms": 3503.27,
  "min_response_time_ms": 30.0,
  "max_response_time_ms": 20022.02,
  "last_10_avg_response_time_ms": 7425.64,
  "last_10_successful": 10,
  "last_10_failed": 0,
  "last_10_success_rate": 100.0,
  "last_10_values": [
    {
      "measurement": 1,
      "timestamp": "2025-11-24T21:05:46",
      "response_time_ms": 42.03,
      "success": true
    },
    {
      "measurement": 2,
      "timestamp": "2025-11-24T21:06:49",
      "response_time_ms": 13514.59,
      "success": true
    },
    {
      "measurement": 3,
      "timestamp": "2025-11-24T21:08:04",
      "response_time_ms": 11609.99,
      "success": true
    },
    {
      "measurement": 4,
      "timestamp": "2025-11-24T21:09:18",
      "response_time_ms": 8302.13,
      "success": true
    },
    {
      "measurement": 5,
      "timestamp": "2025-11-24T21:10:29",
      "response_time_ms": 50.74,
      "success": true
    },
    {
      "measurement": 6,
      "timestamp": "2025-11-24T21:11:31",
      "response_time_ms": 7749.54,
      "success": true
    },
    {
      "measurement": 7,
      "timestamp": "2025-11-24T21:12:41",
      "response_time_ms": 7650.62,
      "success": true
    },
    {
      "measurement": 8,
      "timestamp": "2025-11-24T21:13:51",
      "response_time_ms": 8079.39,
      "success": true
    },
    {
      "measurement": 9,
      "timestamp": "2025-11-24T21:15:02",
      "response_time_ms": 8923.61,
      "success": true
    },
    {
      "measurement": 10,
      "timestamp": "2025-11-24T21:16:13",
      "response_time_ms": 8333.8,
      "success": true
    }
  ],
  "last_updated": "2025-11-24T21:16:22.387158",
  "checker_version": "1.0"
}