{
  "total_checks": 6396,
  "successful_checks": 6262,
  "failed_checks": 134,
  "success_rate": 97.9,
  "avg_response_time_ms": 4330.73,
  "median_response_time_ms": 3359.47,
  "min_response_time_ms": 32.35,
  "max_response_time_ms": 15097.51,
  "last_10_avg_response_time_ms": 7249.77,
  "last_10_successful": 10,
  "last_10_failed": 0,
  "last_10_success_rate": 100.0,
  "last_10_values": [
    {
      "measurement": 1,
      "timestamp": "2025-10-08T13:32:03",
      "response_time_ms": 9104.39,
      "success": true
    },
    {
      "measurement": 2,
      "timestamp": "2025-10-08T13:33:14",
      "response_time_ms": 9926.99,
      "success": true
    },
    {
      "measurement": 3,
      "timestamp": "2025-10-08T13:34:25",
      "response_time_ms": 11490.24,
      "success": true
    },
    {
      "measurement": 4,
      "timestamp": "2025-10-08T13:35:39",
      "response_time_ms": 9549.75,
      "success": true
    },
    {
      "measurement": 5,
      "timestamp": "2025-10-08T13:36:50",
      "response_time_ms": 33.55,
      "success": true
    },
    {
      "measurement": 6,
      "timestamp": "2025-10-08T13:37:52",
      "response_time_ms": 8942.28,
      "success": true
    },
    {
      "measurement": 7,
      "timestamp": "2025-10-08T13:39:02",
      "response_time_ms": 10939.97,
      "success": true
    },
    {
      "measurement": 8,
      "timestamp": "2025-10-08T13:40:15",
      "response_time_ms": 12442.94,
      "success": true
    },
    {
      "measurement": 9,
      "timestamp": "2025-10-08T13:41:29",
      "response_time_ms": 34.63,
      "success": true
    },
    {
      "measurement": 10,
      "timestamp": "2025-10-08T13:42:31",
      "response_time_ms": 32.98,
      "success": true
    }
  ],
  "last_updated": "2025-10-08T13:42:31.606823",
  "checker_version": "1.0"
}