{
  "total_checks": 39666,
  "successful_checks": 39326,
  "failed_checks": 340,
  "success_rate": 99.1,
  "avg_response_time_ms": 4365.16,
  "median_response_time_ms": 3523.86,
  "min_response_time_ms": 30.0,
  "max_response_time_ms": 20022.02,
  "last_10_avg_response_time_ms": 2133.23,
  "last_10_successful": 10,
  "last_10_failed": 0,
  "last_10_success_rate": 100.0,
  "last_10_values": [
    {
      "measurement": 1,
      "timestamp": "2025-11-22T20:23:16",
      "response_time_ms": 1575.17,
      "success": true
    },
    {
      "measurement": 2,
      "timestamp": "2025-11-22T20:24:20",
      "response_time_ms": 1631.81,
      "success": true
    },
    {
      "measurement": 3,
      "timestamp": "2025-11-22T20:25:24",
      "response_time_ms": 1340.87,
      "success": true
    },
    {
      "measurement": 4,
      "timestamp": "2025-11-22T20:26:27",
      "response_time_ms": 799.87,
      "success": true
    },
    {
      "measurement": 5,
      "timestamp": "2025-11-22T20:27:30",
      "response_time_ms": 2080.47,
      "success": true
    },
    {
      "measurement": 6,
      "timestamp": "2025-11-22T20:28:34",
      "response_time_ms": 2198.8,
      "success": true
    },
    {
      "measurement": 7,
      "timestamp": "2025-11-22T20:29:39",
      "response_time_ms": 2302.36,
      "success": true
    },
    {
      "measurement": 8,
      "timestamp": "2025-11-22T20:30:43",
      "response_time_ms": 3647.04,
      "success": true
    },
    {
      "measurement": 9,
      "timestamp": "2025-11-22T20:31:49",
      "response_time_ms": 3380.2,
      "success": true
    },
    {
      "measurement": 10,
      "timestamp": "2025-11-22T20:32:55",
      "response_time_ms": 2375.73,
      "success": true
    }
  ],
  "last_updated": "2025-11-22T20:32:58.044905",
  "checker_version": "1.0"
}