{
  "total_checks": 923,
  "successful_checks": 919,
  "failed_checks": 4,
  "success_rate": 99.6,
  "avg_response_time_ms": 5507.17,
  "median_response_time_ms": 5301.9,
  "min_response_time_ms": 30.45,
  "max_response_time_ms": 15016.37,
  "last_10_avg_response_time_ms": 7031.9,
  "last_10_successful": 10,
  "last_10_failed": 0,
  "last_10_success_rate": 100.0,
  "last_10_values": [
    {
      "measurement": 1,
      "timestamp": "2025-10-24T02:17:55",
      "response_time_ms": 8389.41,
      "success": true
    },
    {
      "measurement": 2,
      "timestamp": "2025-10-24T02:19:05",
      "response_time_ms": 6416.75,
      "success": true
    },
    {
      "measurement": 3,
      "timestamp": "2025-10-24T02:20:13",
      "response_time_ms": 48.45,
      "success": true
    },
    {
      "measurement": 4,
      "timestamp": "2025-10-24T02:21:14",
      "response_time_ms": 9266.21,
      "success": true
    },
    {
      "measurement": 5,
      "timestamp": "2025-10-24T02:22:25",
      "response_time_ms": 47.49,
      "success": true
    },
    {
      "measurement": 6,
      "timestamp": "2025-10-24T02:23:27",
      "response_time_ms": 8094.39,
      "success": true
    },
    {
      "measurement": 7,
      "timestamp": "2025-10-24T02:24:37",
      "response_time_ms": 8988.74,
      "success": true
    },
    {
      "measurement": 8,
      "timestamp": "2025-10-24T02:25:48",
      "response_time_ms": 11017.3,
      "success": true
    },
    {
      "measurement": 9,
      "timestamp": "2025-10-24T02:27:00",
      "response_time_ms": 8917.03,
      "success": true
    },
    {
      "measurement": 10,
      "timestamp": "2025-10-24T02:28:11",
      "response_time_ms": 9133.24,
      "success": true
    }
  ],
  "last_updated": "2025-10-24T02:28:20.712979",
  "checker_version": "1.0"
}