{
  "total_checks": 43252,
  "successful_checks": 42843,
  "failed_checks": 409,
  "success_rate": 99.1,
  "avg_response_time_ms": 4413.48,
  "median_response_time_ms": 3541.86,
  "min_response_time_ms": 30.0,
  "max_response_time_ms": 20022.02,
  "last_10_avg_response_time_ms": 5697.58,
  "last_10_successful": 10,
  "last_10_failed": 0,
  "last_10_success_rate": 100.0,
  "last_10_values": [
    {
      "measurement": 1,
      "timestamp": "2025-11-25T15:19:32",
      "response_time_ms": 8463.35,
      "success": true
    },
    {
      "measurement": 2,
      "timestamp": "2025-11-25T15:20:42",
      "response_time_ms": 5430.05,
      "success": true
    },
    {
      "measurement": 3,
      "timestamp": "2025-11-25T15:21:50",
      "response_time_ms": 7703.04,
      "success": true
    },
    {
      "measurement": 4,
      "timestamp": "2025-11-25T15:23:00",
      "response_time_ms": 4780.9,
      "success": true
    },
    {
      "measurement": 5,
      "timestamp": "2025-11-25T15:24:07",
      "response_time_ms": 4757.09,
      "success": true
    },
    {
      "measurement": 6,
      "timestamp": "2025-11-25T15:25:14",
      "response_time_ms": 3566.03,
      "success": true
    },
    {
      "measurement": 7,
      "timestamp": "2025-11-25T15:26:20",
      "response_time_ms": 6092.36,
      "success": true
    },
    {
      "measurement": 8,
      "timestamp": "2025-11-25T15:27:28",
      "response_time_ms": 5578.74,
      "success": true
    },
    {
      "measurement": 9,
      "timestamp": "2025-11-25T15:28:36",
      "response_time_ms": 4727.39,
      "success": true
    },
    {
      "measurement": 10,
      "timestamp": "2025-11-25T15:29:43",
      "response_time_ms": 5876.89,
      "success": true
    }
  ],
  "last_updated": "2025-11-25T15:29:50.041061",
  "checker_version": "1.0"
}