{
  "total_checks": 57394,
  "successful_checks": 56830,
  "failed_checks": 564,
  "success_rate": 99.0,
  "avg_response_time_ms": 4518.06,
  "median_response_time_ms": 3711.44,
  "min_response_time_ms": 30.0,
  "max_response_time_ms": 20022.02,
  "last_10_avg_response_time_ms": 266.34,
  "last_10_successful": 10,
  "last_10_failed": 0,
  "last_10_success_rate": 100.0,
  "last_10_values": [
    {
      "measurement": 1,
      "timestamp": "2025-12-06T15:20:29",
      "response_time_ms": 389.68,
      "success": true
    },
    {
      "measurement": 2,
      "timestamp": "2025-12-06T15:21:32",
      "response_time_ms": 224.39,
      "success": true
    },
    {
      "measurement": 3,
      "timestamp": "2025-12-06T15:22:34",
      "response_time_ms": 260.16,
      "success": true
    },
    {
      "measurement": 4,
      "timestamp": "2025-12-06T15:23:37",
      "response_time_ms": 271.9,
      "success": true
    },
    {
      "measurement": 5,
      "timestamp": "2025-12-06T15:24:40",
      "response_time_ms": 205.48,
      "success": true
    },
    {
      "measurement": 6,
      "timestamp": "2025-12-06T15:25:42",
      "response_time_ms": 266.61,
      "success": true
    },
    {
      "measurement": 7,
      "timestamp": "2025-12-06T15:26:45",
      "response_time_ms": 280.37,
      "success": true
    },
    {
      "measurement": 8,
      "timestamp": "2025-12-06T15:27:48",
      "response_time_ms": 198.66,
      "success": true
    },
    {
      "measurement": 9,
      "timestamp": "2025-12-06T15:28:50",
      "response_time_ms": 224.76,
      "success": true
    },
    {
      "measurement": 10,
      "timestamp": "2025-12-06T15:29:53",
      "response_time_ms": 341.36,
      "success": true
    }
  ],
  "last_updated": "2025-12-06T15:29:54.640239",
  "checker_version": "1.0"
}