{
  "total_checks": 17518,
  "successful_checks": 17393,
  "failed_checks": 125,
  "success_rate": 99.3,
  "avg_response_time_ms": 4504.68,
  "median_response_time_ms": 3700.24,
  "min_response_time_ms": 30.0,
  "max_response_time_ms": 20022.02,
  "last_10_avg_response_time_ms": 2860.24,
  "last_10_successful": 10,
  "last_10_failed": 0,
  "last_10_success_rate": 100.0,
  "last_10_values": [
    {
      "measurement": 1,
      "timestamp": "2025-11-05T20:09:01",
      "response_time_ms": 3507.71,
      "success": true
    },
    {
      "measurement": 2,
      "timestamp": "2025-11-05T20:10:07",
      "response_time_ms": 3117.6,
      "success": true
    },
    {
      "measurement": 3,
      "timestamp": "2025-11-05T20:11:12",
      "response_time_ms": 2229.01,
      "success": true
    },
    {
      "measurement": 4,
      "timestamp": "2025-11-05T20:12:16",
      "response_time_ms": 2367.04,
      "success": true
    },
    {
      "measurement": 5,
      "timestamp": "2025-11-05T20:13:20",
      "response_time_ms": 2673.25,
      "success": true
    },
    {
      "measurement": 6,
      "timestamp": "2025-11-05T20:14:25",
      "response_time_ms": 1695.72,
      "success": true
    },
    {
      "measurement": 7,
      "timestamp": "2025-11-05T20:15:28",
      "response_time_ms": 5806.4,
      "success": true
    },
    {
      "measurement": 8,
      "timestamp": "2025-11-05T20:16:36",
      "response_time_ms": 2709.76,
      "success": true
    },
    {
      "measurement": 9,
      "timestamp": "2025-11-05T20:17:40",
      "response_time_ms": 1760.38,
      "success": true
    },
    {
      "measurement": 10,
      "timestamp": "2025-11-05T20:18:44",
      "response_time_ms": 2735.55,
      "success": true
    }
  ],
  "last_updated": "2025-11-05T20:18:47.658977",
  "checker_version": "1.0"
}