{
  "total_checks": 33809,
  "successful_checks": 33525,
  "failed_checks": 284,
  "success_rate": 99.2,
  "avg_response_time_ms": 4288.3,
  "median_response_time_ms": 3399.76,
  "min_response_time_ms": 30.0,
  "max_response_time_ms": 20022.02,
  "last_10_avg_response_time_ms": 41.52,
  "last_10_successful": 10,
  "last_10_failed": 0,
  "last_10_success_rate": 100.0,
  "last_10_values": [
    {
      "measurement": 1,
      "timestamp": "2025-11-18T07:10:40",
      "response_time_ms": 42.75,
      "success": true
    },
    {
      "measurement": 2,
      "timestamp": "2025-11-18T07:11:43",
      "response_time_ms": 43.55,
      "success": true
    },
    {
      "measurement": 3,
      "timestamp": "2025-11-18T07:12:45",
      "response_time_ms": 41.47,
      "success": true
    },
    {
      "measurement": 4,
      "timestamp": "2025-11-18T07:13:47",
      "response_time_ms": 40.57,
      "success": true
    },
    {
      "measurement": 5,
      "timestamp": "2025-11-18T07:14:49",
      "response_time_ms": 41.76,
      "success": true
    },
    {
      "measurement": 6,
      "timestamp": "2025-11-18T07:15:52",
      "response_time_ms": 40.34,
      "success": true
    },
    {
      "measurement": 7,
      "timestamp": "2025-11-18T07:16:54",
      "response_time_ms": 39.57,
      "success": true
    },
    {
      "measurement": 8,
      "timestamp": "2025-11-18T07:17:56",
      "response_time_ms": 41.83,
      "success": true
    },
    {
      "measurement": 9,
      "timestamp": "2025-11-18T07:18:58",
      "response_time_ms": 40.31,
      "success": true
    },
    {
      "measurement": 10,
      "timestamp": "2025-11-18T07:20:00",
      "response_time_ms": 43.07,
      "success": true
    }
  ],
  "last_updated": "2025-11-18T07:20:01.301367",
  "checker_version": "1.0"
}