{
  "total_checks": 8313,
  "successful_checks": 8166,
  "failed_checks": 147,
  "success_rate": 98.2,
  "avg_response_time_ms": 4499.27,
  "median_response_time_ms": 3628.74,
  "min_response_time_ms": 31.11,
  "max_response_time_ms": 15097.51,
  "last_10_avg_response_time_ms": 4967.95,
  "last_10_successful": 10,
  "last_10_failed": 0,
  "last_10_success_rate": 100.0,
  "last_10_values": [
    {
      "measurement": 1,
      "timestamp": "2025-10-10T01:08:49",
      "response_time_ms": 6515.75,
      "success": true
    },
    {
      "measurement": 2,
      "timestamp": "2025-10-10T01:09:58",
      "response_time_ms": 7789.09,
      "success": true
    },
    {
      "measurement": 3,
      "timestamp": "2025-10-10T01:11:07",
      "response_time_ms": 38.57,
      "success": true
    },
    {
      "measurement": 4,
      "timestamp": "2025-10-10T01:12:09",
      "response_time_ms": 5723.16,
      "success": true
    },
    {
      "measurement": 5,
      "timestamp": "2025-10-10T01:13:17",
      "response_time_ms": 5083.25,
      "success": true
    },
    {
      "measurement": 6,
      "timestamp": "2025-10-10T01:14:24",
      "response_time_ms": 5021.91,
      "success": true
    },
    {
      "measurement": 7,
      "timestamp": "2025-10-10T01:15:31",
      "response_time_ms": 4870.19,
      "success": true
    },
    {
      "measurement": 8,
      "timestamp": "2025-10-10T01:16:37",
      "response_time_ms": 4955.42,
      "success": true
    },
    {
      "measurement": 9,
      "timestamp": "2025-10-10T01:17:44",
      "response_time_ms": 5044.12,
      "success": true
    },
    {
      "measurement": 10,
      "timestamp": "2025-10-10T01:18:51",
      "response_time_ms": 4638.07,
      "success": true
    }
  ],
  "last_updated": "2025-10-10T01:18:56.256552",
  "checker_version": "1.0"
}