{
  "total_checks": 22963,
  "successful_checks": 22817,
  "failed_checks": 146,
  "success_rate": 99.4,
  "avg_response_time_ms": 4269.9,
  "median_response_time_ms": 3405.44,
  "min_response_time_ms": 30.0,
  "max_response_time_ms": 20022.02,
  "last_10_avg_response_time_ms": 6266.81,
  "last_10_successful": 10,
  "last_10_failed": 0,
  "last_10_success_rate": 100.0,
  "last_10_values": [
    {
      "measurement": 1,
      "timestamp": "2025-11-09T23:11:26",
      "response_time_ms": 5820.27,
      "success": true
    },
    {
      "measurement": 2,
      "timestamp": "2025-11-09T23:12:33",
      "response_time_ms": 4940.06,
      "success": true
    },
    {
      "measurement": 3,
      "timestamp": "2025-11-09T23:13:40",
      "response_time_ms": 5084.21,
      "success": true
    },
    {
      "measurement": 4,
      "timestamp": "2025-11-09T23:14:47",
      "response_time_ms": 8173.95,
      "success": true
    },
    {
      "measurement": 5,
      "timestamp": "2025-11-09T23:15:57",
      "response_time_ms": 8244.81,
      "success": true
    },
    {
      "measurement": 6,
      "timestamp": "2025-11-09T23:17:07",
      "response_time_ms": 45.64,
      "success": true
    },
    {
      "measurement": 7,
      "timestamp": "2025-11-09T23:18:09",
      "response_time_ms": 7247.36,
      "success": true
    },
    {
      "measurement": 8,
      "timestamp": "2025-11-09T23:19:18",
      "response_time_ms": 7126.15,
      "success": true
    },
    {
      "measurement": 9,
      "timestamp": "2025-11-09T23:20:28",
      "response_time_ms": 10010.8,
      "success": true
    },
    {
      "measurement": 10,
      "timestamp": "2025-11-09T23:21:39",
      "response_time_ms": 5974.88,
      "success": true
    }
  ],
  "last_updated": "2025-11-09T23:21:46.111804",
  "checker_version": "1.0"
}