{
  "total_checks": 15295,
  "successful_checks": 15180,
  "failed_checks": 115,
  "success_rate": 99.2,
  "avg_response_time_ms": 4397.29,
  "median_response_time_ms": 3625.1,
  "min_response_time_ms": 30.0,
  "max_response_time_ms": 20022.02,
  "last_10_avg_response_time_ms": 7506.93,
  "last_10_successful": 10,
  "last_10_failed": 0,
  "last_10_success_rate": 100.0,
  "last_10_values": [
    {
      "measurement": 1,
      "timestamp": "2025-11-04T02:39:24",
      "response_time_ms": 7934.51,
      "success": true
    },
    {
      "measurement": 2,
      "timestamp": "2025-11-04T02:40:34",
      "response_time_ms": 9488.4,
      "success": true
    },
    {
      "measurement": 3,
      "timestamp": "2025-11-04T02:41:46",
      "response_time_ms": 9311.61,
      "success": true
    },
    {
      "measurement": 4,
      "timestamp": "2025-11-04T02:42:57",
      "response_time_ms": 10298.99,
      "success": true
    },
    {
      "measurement": 5,
      "timestamp": "2025-11-04T02:44:09",
      "response_time_ms": 8433.36,
      "success": true
    },
    {
      "measurement": 6,
      "timestamp": "2025-11-04T02:45:19",
      "response_time_ms": 32.82,
      "success": true
    },
    {
      "measurement": 7,
      "timestamp": "2025-11-04T02:46:21",
      "response_time_ms": 9212.77,
      "success": true
    },
    {
      "measurement": 8,
      "timestamp": "2025-11-04T02:47:32",
      "response_time_ms": 10208.74,
      "success": true
    },
    {
      "measurement": 9,
      "timestamp": "2025-11-04T02:48:44",
      "response_time_ms": 32.03,
      "success": true
    },
    {
      "measurement": 10,
      "timestamp": "2025-11-04T02:49:46",
      "response_time_ms": 10116.11,
      "success": true
    }
  ],
  "last_updated": "2025-11-04T02:49:56.393914",
  "checker_version": "1.0"
}