{
  "total_checks": 3206,
  "successful_checks": 3198,
  "failed_checks": 8,
  "success_rate": 99.8,
  "avg_response_time_ms": 3508.83,
  "median_response_time_ms": 2598.03,
  "min_response_time_ms": 32.35,
  "max_response_time_ms": 15078.04,
  "last_10_avg_response_time_ms": 4426.02,
  "last_10_successful": 10,
  "last_10_failed": 0,
  "last_10_success_rate": 100.0,
  "last_10_values": [
    {
      "measurement": 1,
      "timestamp": "2025-10-05T23:05:47",
      "response_time_ms": 6499.0,
      "success": true
    },
    {
      "measurement": 2,
      "timestamp": "2025-10-05T23:06:55",
      "response_time_ms": 5948.28,
      "success": true
    },
    {
      "measurement": 3,
      "timestamp": "2025-10-05T23:08:03",
      "response_time_ms": 4994.09,
      "success": true
    },
    {
      "measurement": 4,
      "timestamp": "2025-10-05T23:09:10",
      "response_time_ms": 3646.59,
      "success": true
    },
    {
      "measurement": 5,
      "timestamp": "2025-10-05T23:10:15",
      "response_time_ms": 4868.68,
      "success": true
    },
    {
      "measurement": 6,
      "timestamp": "2025-10-05T23:11:21",
      "response_time_ms": 3741.5,
      "success": true
    },
    {
      "measurement": 7,
      "timestamp": "2025-10-05T23:12:27",
      "response_time_ms": 3685.03,
      "success": true
    },
    {
      "measurement": 8,
      "timestamp": "2025-10-05T23:13:32",
      "response_time_ms": 3755.08,
      "success": true
    },
    {
      "measurement": 9,
      "timestamp": "2025-10-05T23:14:38",
      "response_time_ms": 3697.11,
      "success": true
    },
    {
      "measurement": 10,
      "timestamp": "2025-10-05T23:15:43",
      "response_time_ms": 3424.85,
      "success": true
    }
  ],
  "last_updated": "2025-10-05T23:15:47.179955",
  "checker_version": "1.0"
}