{
  "total_checks": 36119,
  "successful_checks": 35810,
  "failed_checks": 309,
  "success_rate": 99.1,
  "avg_response_time_ms": 4326.94,
  "median_response_time_ms": 3456.37,
  "min_response_time_ms": 30.0,
  "max_response_time_ms": 20022.02,
  "last_10_avg_response_time_ms": 7722.4,
  "last_10_successful": 10,
  "last_10_failed": 0,
  "last_10_success_rate": 100.0,
  "last_10_values": [
    {
      "measurement": 1,
      "timestamp": "2025-11-20T02:12:54",
      "response_time_ms": 9795.01,
      "success": true
    },
    {
      "measurement": 2,
      "timestamp": "2025-11-20T02:14:06",
      "response_time_ms": 10133.23,
      "success": true
    },
    {
      "measurement": 3,
      "timestamp": "2025-11-20T02:15:18",
      "response_time_ms": 10817.89,
      "success": true
    },
    {
      "measurement": 4,
      "timestamp": "2025-11-20T02:16:31",
      "response_time_ms": 9975.39,
      "success": true
    },
    {
      "measurement": 5,
      "timestamp": "2025-11-20T02:17:43",
      "response_time_ms": 9029.28,
      "success": true
    },
    {
      "measurement": 6,
      "timestamp": "2025-11-20T02:18:54",
      "response_time_ms": 7882.14,
      "success": true
    },
    {
      "measurement": 7,
      "timestamp": "2025-11-20T02:20:04",
      "response_time_ms": 9358.82,
      "success": true
    },
    {
      "measurement": 8,
      "timestamp": "2025-11-20T02:21:16",
      "response_time_ms": 46.23,
      "success": true
    },
    {
      "measurement": 9,
      "timestamp": "2025-11-20T02:22:18",
      "response_time_ms": 10138.59,
      "success": true
    },
    {
      "measurement": 10,
      "timestamp": "2025-11-20T02:23:30",
      "response_time_ms": 47.43,
      "success": true
    }
  ],
  "last_updated": "2025-11-20T02:23:31.079708",
  "checker_version": "1.0"
}