{
  "total_checks": 7380,
  "successful_checks": 7236,
  "failed_checks": 144,
  "success_rate": 98.0,
  "avg_response_time_ms": 4439.28,
  "median_response_time_ms": 3552.58,
  "min_response_time_ms": 31.11,
  "max_response_time_ms": 15097.51,
  "last_10_avg_response_time_ms": 5232.6,
  "last_10_successful": 10,
  "last_10_failed": 0,
  "last_10_success_rate": 100.0,
  "last_10_values": [
    {
      "measurement": 1,
      "timestamp": "2025-10-09T07:49:38",
      "response_time_ms": 9490.6,
      "success": true
    },
    {
      "measurement": 2,
      "timestamp": "2025-10-09T07:50:50",
      "response_time_ms": 44.67,
      "success": true
    },
    {
      "measurement": 3,
      "timestamp": "2025-10-09T07:51:51",
      "response_time_ms": 44.37,
      "success": true
    },
    {
      "measurement": 4,
      "timestamp": "2025-10-09T07:52:53",
      "response_time_ms": 10153.95,
      "success": true
    },
    {
      "measurement": 5,
      "timestamp": "2025-10-09T07:54:05",
      "response_time_ms": 9610.56,
      "success": true
    },
    {
      "measurement": 6,
      "timestamp": "2025-10-09T07:55:16",
      "response_time_ms": 9647.96,
      "success": true
    },
    {
      "measurement": 7,
      "timestamp": "2025-10-09T07:56:28",
      "response_time_ms": 43.36,
      "success": true
    },
    {
      "measurement": 8,
      "timestamp": "2025-10-09T07:57:30",
      "response_time_ms": 13152.98,
      "success": true
    },
    {
      "measurement": 9,
      "timestamp": "2025-10-09T07:58:44",
      "response_time_ms": 46.72,
      "success": true
    },
    {
      "measurement": 10,
      "timestamp": "2025-10-09T07:59:46",
      "response_time_ms": 90.79,
      "success": true
    }
  ],
  "last_updated": "2025-10-09T07:59:46.856132",
  "checker_version": "1.0"
}